visualdl/__init__.py
visualdl/version.py
visualdl/component/__init__.py
visualdl/component/base_component.py
visualdl/component/graph/__init__.py
visualdl/component/graph/exporter.py
visualdl/component/graph/graph_component.py
visualdl/component/graph/netron_graph.py
visualdl/component/graph/utils.py
visualdl/component/inference/__init__.py
visualdl/component/inference/fastdeploy_lib.py
visualdl/component/inference/fastdeploy_server.py
visualdl/component/inference/model_convert_server.py
visualdl/component/inference/xarfile.py
visualdl/component/inference/fastdeploy_client/__init__.py
visualdl/component/inference/fastdeploy_client/client_app.py
visualdl/component/inference/fastdeploy_client/http_client_manager.py
visualdl/component/inference/fastdeploy_client/visualizer.py
visualdl/component/inference/proto/__init__.py
visualdl/component/inference/proto/model_config_pb2.py
visualdl/component/profiler/__init__.py
visualdl/component/profiler/profiler_data.py
visualdl/component/profiler/profiler_reader.py
visualdl/component/profiler/profiler_server.py
visualdl/component/profiler/run_manager.py
visualdl/component/profiler/parser/__init__.py
visualdl/component/profiler/parser/const_description.py
visualdl/component/profiler/parser/distributed_parser.py
visualdl/component/profiler/parser/event_node.py
visualdl/component/profiler/parser/kernel_parser.py
visualdl/component/profiler/parser/memory_parser.py
visualdl/component/profiler/parser/operator_parser.py
visualdl/component/profiler/parser/overview_parser.py
visualdl/component/profiler/parser/trace_parser.py
visualdl/component/profiler/parser/utils.py
visualdl/io/__init__.py
visualdl/io/bfile.py
visualdl/io/bos_conf.py
visualdl/proto/__init__.py
visualdl/proto/record_pb2.py
visualdl/python/__init__.py
visualdl/python/cache.py
visualdl/python/testing.wav
visualdl/reader/__init__.py
visualdl/reader/graph_reader.py
visualdl/reader/reader.py
visualdl/reader/record_reader.py
visualdl/server/__init__.py
visualdl/server/api.py
visualdl-2.5.1.dist-info/LICENSE
visualdl-2.5.1.dist-info/METADATA
visualdl-2.5.1.dist-info/WHEEL
visualdl-2.5.1.dist-info/entry_points.txt
visualdl-2.5.1.dist-info/top_level.txt
visualdl-2.5.1.dist-info/RECORD
