Metadata-Version: 2.1
Name: visualdl
Version: 2.5.1
Summary: Visualize Deep Learning
Home-page: UNKNOWN
Author: PaddlePaddle and Echarts team
License: Apache License
Keywords: visualization deeplearning
Platform: UNKNOWN
Requires-Dist: bce-python-sdk
Requires-Dist: flask (>=1.1.1)
Requires-Dist: Flask-Babel (>=3.0.0)
Requires-Dist: numpy
Requires-Dist: Pillow (>=7.0.0)
Requires-Dist: protobuf (>=3.20.0)
Requires-Dist: requests
Requires-Dist: six (>=1.14.0)
Requires-Dist: matplotlib
Requires-Dist: pandas
Requires-Dist: packaging
Requires-Dist: x2paddle
Requires-Dist: rarfile
Requires-Dist: gradio
Requires-Dist: tritonclient[all]
Requires-Dist: attrdict
Requires-Dist: psutil
Requires-Dist: onnx (>=1.6.0)
